fast_sentence_segment/__init__.py
fast_sentence_segment/bp/__init__.py
fast_sentence_segment/bp/segmenter.py
fast_sentence_segment/cli.py
fast_sentence_segment/core/__init__.py
fast_sentence_segment/core/base_object.py
fast_sentence_segment/core/stopwatch.py
fast_sentence_segment/dmo/__init__.py
fast_sentence_segment/dmo/abbreviation_merger.py
fast_sentence_segment/dmo/abbreviation_splitter.py
fast_sentence_segment/dmo/abbreviations.py
fast_sentence_segment/dmo/bullet_point_cleaner.py
fast_sentence_segment/dmo/ellipsis_normalizer.py
fast_sentence_segment/dmo/group_quoted_sentences.py
fast_sentence_segment/dmo/newlines_to_periods.py
fast_sentence_segment/dmo/normalize_quotes.py
fast_sentence_segment/dmo/numbered_list_normalizer.py
fast_sentence_segment/dmo/post_process_sentences.py
fast_sentence_segment/dmo/question_exclamation_splitter.py
fast_sentence_segment/dmo/spacy_doc_segmenter.py
fast_sentence_segment/dmo/strip_trailing_period_after_quote.py
fast_sentence_segment/dmo/title_name_merger.py
fast_sentence_segment/dmo/unwrap_hard_wrapped_text.py
fast_sentence_segment/svc/__init__.py
fast_sentence_segment/svc/perform_paragraph_segmentation.py
fast_sentence_segment/svc/perform_sentence_segmentation.py
fast_sentence_segment-1.3.0.dist-info/LICENSE
fast_sentence_segment-1.3.0.dist-info/METADATA
fast_sentence_segment-1.3.0.dist-info/WHEEL
fast_sentence_segment-1.3.0.dist-info/entry_points.txt
fast_sentence_segment-1.3.0.dist-info/RECORD
