Metadata-Version: 2.1
Name: fast-sentence-segment
Version: 1.3.0
Summary: Fast and Efficient Sentence Segmentation
Home-page: https://github.com/craigtrim/fast-sentence-segment
License: MIT
Keywords: nlp,text,preprocess,segment
Author: Craig Trim
Author-email: craigtrim@gmail.com
Maintainer: Craig Trim
Maintainer-email: craigtrim@gmail.com
Requires-Python: >=3.9,<4.0
Classifier: Development Status :: 5 - Production/Stable
Classifier: Intended Audience :: Developers
Classifier: Intended Audience :: Science/Research
Classifier: License :: OSI Approved :: MIT License
Classifier: Operating System :: OS Independent
Classifier: Programming Language :: Python :: 3
Classifier: Programming Language :: Python :: 3.9
Classifier: Programming Language :: Python :: 3.10
Classifier: Programming Language :: Python :: 3.11
Classifier: Programming Language :: Python :: 3.12
Classifier: Topic :: Scientific/Engineering :: Artificial Intelligence
Classifier: Topic :: Software Development :: Libraries :: Python Modules
Classifier: Topic :: Text Processing :: Linguistic
Classifier: Typing :: Typed
Requires-Dist: spacy (>=3.8.0,<4.0.0)
Project-URL: Bug Tracker, https://github.com/craigtrim/fast-sentence-segment/issues
Project-URL: Repository, https://github.com/craigtrim/fast-sentence-segment
